[
  {
    "contentCategory": "BOOKS",
    "searchFields": [
      "name",
      "author",
      "synopsis"
    ]
  },
  {
    "contentCategory": "COMPANIES",
    "searchFields": [
      "rank",
      "name",
      "country",
      "headquarters",
      "industry",
      "sector",
      "ceo",
      "employees",
      "founded",
      "website",
      "description"
    ]
  },
  {
    "contentCategory": "MOVIES",
    "searchFields": [
      "name",
      "director",
      "synopsis"
    ]
  },
  {
    "contentCategory": "MUSIC",
    "searchFields": [
      "band",
      "album",
      "name",
      "lyrics"
    ]
  }
]